zwf.py
zwf-0.1.0.dist-info/entry_points.txt
zwf-0.1.0.dist-info/LICENSE
zwf-0.1.0.dist-info/WHEEL
zwf-0.1.0.dist-info/METADATA
zwf-0.1.0.dist-info/RECORD
