Metadata-Version: 2.1
Name: zwf
Version: 0.1.0
Summary: Tools for Zwift WAD files
Home-page: https://github.com/h4l/zwf
License: MIT
Author: Hal Blackburn
Author-email: hal.blackburn@gmail.com
Requires-Python: >=3.6,<4.0
Classifier: License :: OSI Approved :: MIT License
Classifier: Programming Language :: Python :: 3
Classifier: Programming Language :: Python :: 3 :: Only
Classifier: Programming Language :: Python :: 3.6
Classifier: Programming Language :: Python :: 3.7
Classifier: Programming Language :: Python :: 3.8
Classifier: Programming Language :: Python :: 3.9
Requires-Dist: docopt (>=0.6.2,<0.7.0)
Requires-Dist: hurry.filesize (>=0.9,<0.10)
